{
  "Id": 58,
  "Name": "Turkey. Locative",
  "Lang": null,
  "Content": "{\\rtf1\\ansi\\ansicpg1251\\deff0\\nouicompat\\deflang1049{\\fonttbl{\\f0\\fnil\\fcharset0 Roboto Condensed;}{\\f1\\fnil\\fcharset204 Roboto Condensed;}{\\f2\\fnil\\fcharset162 Roboto Condensed;}{\\f3\\fnil\\fcharset238 Roboto Condensed;}}\r\n{\\colortbl ;\\red255\\green255\\blue0;}\r\n{\\*\\generator Riched20 10.0.19041}\\viewkind4\\uc1 \r\n\\pard\\cf1\\f0\\fs24\\lang1033 ### Turkey. \\f1\\lang1049 Locative\\par\r\n\\par\r\n\\f0\\lang1033 #words:\\f1\\lang1049\\par\r\n\\f2\\lang1055 b\\f0\\lang1033 athroom - \\f2\\lang1055 banyo\\par\r\nhotel - otel\\par\r\nhouse - ev\\par\r\npost office - postane\\par\r\n\\f0\\lang1033 sea - \\f2\\lang1055 deniz\\par\r\nairport - havaliman\\f3\\u305?\\f2\\par\r\npool - havuz\\f1\\lang1049\\par\r\n\\f0\\lang1033 zoo - \\f2\\lang1055 hayvanat bah\\f0\\lang1033\\'e7\\f2\\lang1055 esi\\f1\\lang1049\\par\r\nport\\f2\\lang1055  - liman\\f1\\lang1049\\par\r\n\\f0\\lang1033 museum - \\f2\\lang1055 m\\f0\\lang1033\\'fc\\f2\\lang1055 ze\\par\r\nleft - sol\\par\r\nright - sa\\f3\\u287?\\f1\\lang1049\\par\r\n\\f0\\lang1033 kitchen - \\f2\\lang1055 mutfak\\par\r\n\\f0\\lang1033 breakfast\\f2\\lang1055  \\f0\\lang1033 - \\f2\\lang1055 kahvalt\\f3\\u305?\\f1\\lang1049\\par\r\nfood\\f2\\lang1055  - yemek\\par\r\ncastle - kale\\f1\\lang1049\\par\r\n\\par\r\n\\par\r\n\\par\r\n\\par\r\nBen kilisedeyim, sen neredesin?\\par\r\nRestoranda \\f0\\lang1033\\'e7orba var.\\f2\\lang1055  There is soup at the restaurant.\\par\r\nOtelde ku\\f3\\'balar var.\\f2  \\f0\\lang1033 There are birds at the hotel.\\par\r\nBen okulday\\f3\\u305?m.\\f0  I am at school.\\par\r\nPasta pastanededir, postanede de\\f3\\u287?il.\\f0  The cake is at the bakery, not at the post office.\\par\r\nBen hastanedeyim, sen pastanedesin. I am at the hospital you are at the patisserie.\\par\r\nFil postanede domates yer. The elephant eats a tomato at the post office.\\par\r\nRestoranda \\'e7orba var. There is soup at the restaurant.\\par\r\nBanyo \\'e7ok k\\'fc\\'e7\\'fck.\\f2\\lang1055  \\f0\\lang1033 The bathroom is very small.\\par\r\nSen bakkaldas\\f3\\u305?n.\\f0  You are at the grocery store.\\par\r\nTuvalette \\'f6r\\'fcmcek var. There is a spider in the toilet.\\par\r\nEvin bir odas\\f3\\u305?\\f0 . A room of the house. (\\f1\\lang1049\\'e4\\'ee\\'ec\\'e0 \\'ee\\'e4\\'ed\\'e0 \\'ea\\'ee\\'ec\\'ed\\'e0\\'f2\\'e0\\f0\\lang1033 )\\par\r\nAffedersin, Sultan Ahmet camisi nerede? Excuse me, where is the Blue Mosque?\\par\r\nHavuzda \\'e7ocuklar var.\\f2\\lang1055  \\f0\\lang1033 There are children in the pool.\\par\r\nDenizde kaplumba\\f3\\u287?a yok.\\f2\\lang1055\\par\r\nHayvanat bah\\f0\\lang1033\\'e7esindeyiz.\\f2\\lang1055  We are at the zoo.\\f0\\lang1033\\par\r\nKumsalda bira i\\'e7!\\f2\\lang1055  Drink a beer on the beach!\\f0\\lang1033\\par\r\n\\f1\\lang1049 Kaptan limanda.\\f2\\lang1055  The captain is at the port.\\par\r\nBen havaliman\\f3\\u305?nda onlara kitap okurum.\\f2  I read a book to them at the airport.\\par\r\n\\f3\\u304?stanbul'da \\f0\\lang1033\\'e7ok m\\'fcze var.\\f2\\lang1055  \\f0\\lang1033 There are many museums in Istambul.\\par\r\nSolda bir k\\'f6pek var. There is a dog on the left.\\par\r\nSa\\f3\\u287?\\u305?mda bir ku\\'ba var.\\f0  There is a bird on my right.\\par\r\nAyasofya'n\\f3\\u305?n b\\f0\\'fcy\\'fck bir bah\\'e7esi var. The Hagia Sophia has a big garden.\\par\r\n\\f3\\u304?stanbul T\\f0\\'fcrkiye'nin kuzey bat\\f3\\u305?s\\u305?nda.\\f0  Istanbul is in the northwest of Turkey.\\par\r\nAyasofya'n\\f3\\u305?n kuzeyinde \\f0\\'e7ok m\\'fcze var. There are a lot of museums in the north of the Hagia Sophia.\\par\r\n\\par\r\nKaplumba\\f3\\u287?alar onlarda.\\f0  They have the turtles.\\par\r\n\\par\r\n\\par\r\nK\\'fc\\'e7\\'fck kedi bizde. We have the little cat.\\par\r\nEski \\f3\\'baarap sende.\\f0  You have the old wine.\\par\r\n\\f2\\lang1055 Elmalar sende. \\f0\\lang1033 You have the apples.\\par\r\nPasta onda. She has the cake.\\par\r\nOnlar benim patronlar\\f3\\u305?m.\\f0  Those are my bosses.\\par\r\n\\'d6rdek bende. I have the duck.\\par\r\nG\\'fczel ku\\f3\\'balar onda.\\f0  He has the beautiful birds.\\par\r\nBenim kedim orada.\\f2\\lang1055  \\f0\\lang1033 My cat is there. \\f2\\lang1055 My cat is over there.\\f0\\lang1033\\par\r\n\\'d6\\f3\\u287?renciler kalede.\\f0  The students are in the castle.\\par\r\nBah\\'e7ede, kahvalt\\f3\\u305?day\\u305?m.\\f0  I am in the garden, at breakfast.\\par\r\nBen mutfaktay\\f3\\u305?m.\\f0  I am in the kitchen.\\par\r\nBuras\\f3\\u305? bir postane.\\f0  Here is a post office.\\par\r\nAnkara'da \\'e7ok kedi var. There are many cats in Ankara.\\par\r\nMimar Ankara'da \\'e7ay i\\'e7er. The architect drinks tea in Ankara.\\par\r\nEski postanede k\\'f6pekler var. There are dogs at the old post office.\\par\r\n\\f2\\lang1055 Neden havuzda de\\f3\\u287?\\f2 il. Why is she not in the pool?\\par\r\n\\f0\\lang1033\\'d6\\f2\\lang1055 rdekler denizde. The ducks are in the sea.\\par\r\nLimanda de\\f3\\u287?\\f2 ilim havaliman\\f3\\u305?\\f2 nday\\f3\\u305?\\f2 m. I am not at the port, I am at the airport.\\par\r\nBen havaliman\\f3\\u305?nda onlara kitap okurum.\\f2  \\f3 I read a book to them at the airport.\\f0\\lang1033\\par\r\ngen\\'e7 filler onda\\f2\\lang1055 . She has the young elephants.\\par\r\nBuras\\f3\\u305? bir postane.\\f2  \\f0\\lang1033 Here is a post office.\\par\r\nOrada kim var? Who is there?\\par\r\nKahvalt\\f3\\u305?da kimin \\f0\\'e7ocuklar\\f3\\u305? var?\\f0  Whose children are at the breakfast?\\par\r\nBizim evimiz orada. Our house is there.\\par\r\nBu oda. This room.\\par\r\n\\par\r\n\\par\r\n\\par\r\n\\par\r\n\\par\r\n\\f2\\lang1055\\par\r\n\\par\r\n\\f1\\lang1049\\par\r\n}\r\n",
  "WorkText": "{\\rtf1\\ansi\\ansicpg1251\\deff0\\nouicompat\\deflang1049{\\fonttbl{\\f0\\fnil\\fcharset204 Roboto Condensed;}}\r\n{\\colortbl ;\\red124\\green252\\blue0;}\r\n{\\*\\generator Riched20 10.0.19041}\\viewkind4\\uc1 \r\n\\pard\\cf1\\f0\\fs24\\par\r\n}\r\n",
  "TxtContent": "### Turkey. Locative\n\n#words:\nbathroom - banyo\nhotel - otel\nhouse - ev\npost office - postane\nsea - deniz\nairport - havalimanı\npool - havuz\nzoo - hayvanat bahçesi\nport - liman\nmuseum - müze\nleft - sol\nright - sağ\nkitchen - mutfak\nbreakfast - kahvaltı\nfood - yemek\ncastle - kale\n\n\n\n\nBen kilisedeyim, sen neredesin?\nRestoranda çorba var. There is soup at the restaurant.\nOtelde kuşlar var. There are birds at the hotel.\nBen okuldayım. I am at school.\nPasta pastanededir, postanede değil. The cake is at the bakery, not at the post office.\nBen hastanedeyim, sen pastanedesin. I am at the hospital you are at the patisserie.\nFil postanede domates yer. The elephant eats a tomato at the post office.\nRestoranda çorba var. There is soup at the restaurant.\nBanyo çok küçük. The bathroom is very small.\nSen bakkaldasın. You are at the grocery store.\nTuvalette örümcek var. There is a spider in the toilet.\nEvin bir odası. A room of the house. (дома одна комната)\nAffedersin, Sultan Ahmet camisi nerede? Excuse me, where is the Blue Mosque?\nHavuzda çocuklar var. There are children in the pool.\nDenizde kaplumbağa yok.\nHayvanat bahçesindeyiz. We are at the zoo.\nKumsalda bira iç! Drink a beer on the beach!\nKaptan limanda. The captain is at the port.\nBen havalimanında onlara kitap okurum. I read a book to them at the airport.\nİstanbul'da çok müze var. There are many museums in Istambul.\nSolda bir köpek var. There is a dog on the left.\nSağımda bir kuş var. There is a bird on my right.\nAyasofya'nın büyük bir bahçesi var. The Hagia Sophia has a big garden.\nİstanbul Türkiye'nin kuzey batısında. Istanbul is in the northwest of Turkey.\nAyasofya'nın kuzeyinde çok müze var. There are a lot of museums in the north of the Hagia Sophia.\n\nKaplumbağalar onlarda. They have the turtles.\n\n\nKüçük kedi bizde. We have the little cat.\nEski şarap sende. You have the old wine.\nElmalar sende. You have the apples.\nPasta onda. She has the cake.\nOnlar benim patronlarım. Those are my bosses.\nÖrdek bende. I have the duck.\nGüzel kuşlar onda. He has the beautiful birds.\nBenim kedim orada. My cat is there. My cat is over there.\nÖğrenciler kalede. The students are in the castle.\nBahçede, kahvaltıdayım. I am in the garden, at breakfast.\nBen mutfaktayım. I am in the kitchen.\nBurası bir postane. Here is a post office.\nAnkara'da çok kedi var. There are many cats in Ankara.\nMimar Ankara'da çay içer. The architect drinks tea in Ankara.\nEski postanede köpekler var. There are dogs at the old post office.\nNeden havuzda değil. Why is she not in the pool?\nÖrdekler denizde. The ducks are in the sea.\nLimanda değilim havalimanındayım. I am not at the port, I am at the airport.\nBen havalimanında onlara kitap okurum. I read a book to them at the airport.\ngenç filler onda. She has the young elephants.\nBurası bir postane. Here is a post office.\nOrada kim var? Who is there?\nKahvaltıda kimin çocukları var? Whose children are at the breakfast?\nBizim evimiz orada. Our house is there.\nBu oda. This room.\n\n\n\n\n\n\n\n",
  "DateTime": "0001-01-01T00:00:00"
}